LICENSE
README.txt
setup.py
mcf/__init__.py
mcf/general_purpose.py
mcf/general_purpose_estimation.py
mcf/general_purpose_system_files.py
mcf/mcf_ate_functions.py
mcf/mcf_cs_functions.py
mcf/mcf_data_functions.py
mcf/mcf_forest_add_functions.py
mcf/mcf_forest_functions.py
mcf/mcf_functions.py
mcf/mcf_gate_functions.py
mcf/mcf_gate_out_functions.py
mcf/mcf_gate_tables_functions.py
mcf/mcf_general_purpose.py
mcf/mcf_hf.py
mcf/mcf_iate_add_functions.py
mcf/mcf_iate_cv_functions.py
mcf/mcf_iate_functions.py
mcf/mcf_init_add_functions.py
mcf/mcf_init_functions.py
mcf/mcf_loccent_functions.py
mcf/mcf_vi_functions.py
mcf/mcf_weight_functions.py
mcf/optp_blackbox_functions.py
mcf/optp_functions.py
mcf/optp_mcf_functions.py
mcf/optp_print.py
mcf/optp_tree_add_functions.py
mcf/optp_tree_functions.py
mcf.egg-info/PKG-INFO
mcf.egg-info/SOURCES.txt
mcf.egg-info/dependency_links.txt
mcf.egg-info/requires.txt
mcf.egg-info/top_level.txt