Metadata-Version: 2.1
Name: mcf
Version: 0.3.3
Summary: mcf is a powerful package to estimate heterogeneous treatment effects for multiple treatment models in a selection-on-observables setting and learn optimal policy rules
Home-page: https://github.com/MCFpy/mcf
Author: mlechner
Author-email: michael.lechner@unisg.ch
License: MIT
Keywords: causal machine learning, heterogeneous treatment effects, causal forests, optimal policy learning
Classifier: Development Status :: 5 - Production/Stable
Classifier: Topic :: Software Development :: Build Tools
Classifier: License :: OSI Approved :: MIT License
Classifier: Programming Language :: Python :: 3.10
License-File: LICENSE
